get_pbmr
