Metadata-Version: 1.0
Name: get-pbmr
Version: 0.2.4
Summary: Getting per base mutation rate from SAM and BAM files.
Home-page: UNKNOWN
Author: Semar Petrus
Author-email: UNKNOWN
License: UNKNOWN
Platform: UNKNOWN
